setup.py
Divan.egg-info/PKG-INFO
Divan.egg-info/SOURCES.txt
Divan.egg-info/dependency_links.txt
Divan.egg-info/requires.txt
Divan.egg-info/top_level.txt
divan/__init__.py
divan/attachment.py
divan/connection.py
divan/database.py
divan/document.py
divan/error.py
divan/resource.py
divan/view.py