Metadata-Version: 1.0
Name: Divan
Version: 0.2.3
Summary: Asynchronous Cloudant / CouchDB Interface
Home-page: https://github.com/garbados/divan
Author: Max Thayer
Author-email: garbados@gmail.com
License: UNKNOWN
Platform: UNKNOWN
